pycharm_remote_debugger/__init__.py
pycharm_remote_debugger/__main__.py
pycharm_remote_debugger/_logger.py
pycharm_remote_debugger/_pycharm_remote_debugger.py
pycharm_remote_debugger-0.1.18.dist-info/LICENSE
pycharm_remote_debugger-0.1.18.dist-info/METADATA
pycharm_remote_debugger-0.1.18.dist-info/WHEEL
pycharm_remote_debugger-0.1.18.dist-info/entry_points.txt
pycharm_remote_debugger-0.1.18.dist-info/top_level.txt
pycharm_remote_debugger-0.1.18.dist-info/RECORD
